README.rst
setup.py
servercraft/__init__.py
servercraft/build_server.py
servercraft.egg-info/PKG-INFO
servercraft.egg-info/SOURCES.txt
servercraft.egg-info/dependency_links.txt
servercraft.egg-info/entry_points.txt
servercraft.egg-info/requires.txt
servercraft.egg-info/top_level.txt
servercraft/code_model/__init__.py
servercraft/code_model/models.py
servercraft/code_model/script.py
servercraft/code_model/urls.py
servercraft/code_model/views.py
servercraft/html_model/__init__.py
servercraft/html_model/base_html.py
servercraft/html_model/index_html.py
servercraft/html_model/result_html.py
servercraft/html_model/waiting_html.py