Metadata-Version: 1.1
Name: servercraft
Version: 0.0.2
Summary: Use django to build an online server
Home-page: UNKNOWN
Author: Feng Zhang
Author-email: 15110700005@fudan.edu.cn
License: Apache-2.0
Keywords: django
Platform: UNKNOWN
Classifier: Development Status :: 3 - Alpha
Classifier: Programming Language :: Python :: 2.7
